{
  "entries": [
    {
      "entry": "files/v1alpha2",
      "value": {
        "files": [
          {
            "path": ".babelrc",
            "sha512": "8878f76f0105582ce8ffd74b357ab62f7e0017e6da402ab30c55bc8a30783a88c0705520c81779bc8372a1de335cec7cf2fa9335069561f2912ef403e6f46ff2"
          },
          {
            "path": ".editorconfig",
            "sha512": "67e622eb811b5e4a7c336cfe3a82ae1925c3ac680abaab3c8f1b357b1e7ffe06fbcd27dfa5652083b551f642a4da03687fc4fc529f1749b5f174595671fa6043"
          },
          {
            "path": ".eslintignore",
            "sha512": "cf83e1357eefb8bdf1542850d66d8007d620e4050b5715dc83f4a921d36ce9ce47d0d13c5d85f2b0ff8318d2877eec2f63b931bd47417a81a538327af927da3e"
          },
          {
            "path": ".eslintrc",
            "sha512": "b3d4a79e7d428ed8cffc1045928fd28bac36153b811db30f5ed1dd27b6d8f1f62649c18e9c33ada948870f68b1bc109bc30935762b886c79859cc125c761683c"
          },
          {
            "path": ".gitmodules",
            "sha512": "cf83e1357eefb8bdf1542850d66d8007d620e4050b5715dc83f4a921d36ce9ce47d0d13c5d85f2b0ff8318d2877eec2f63b931bd47417a81a538327af927da3e"
          },
          {
            "path": ".looprc",
            "sha512": "76ab149733dadc84f3f20560dc142127f321ccd5dbcfd9d20940d702e813e755849b1d00b4ca022563ca1f96abd40e5232d467fcb4a980c2ae5d2f61707a1986"
          },
          {
            "path": "LICENSE",
            "sha512": "a0bec7bcfb100e6cb7930ba24fe6f9c6d6aec42606eaa4b9e16bc64358725a03a732cfbb34a733b03c0d5a0bf8bf99d56e882b6d7a9976b748ceb1e3eafd049a"
          },
          {
            "path": "tronbox.dev",
            "sha512": "e57be8cfde455dd62d36946b8b43dcb093c7b95c49bada62c54be4033e5241f5eacdf911c8277802ccdb773e4c47e5ce9ec0cbec04189fe1bd6494e51354cc94"
          },
          {
            "path": "nil.js",
            "sha512": "431eadc16be8e37503bf8e2453039ae4cdb104fd9a2b9ce42a1aec17949d1cf3ea254dea5267fb56911ac01af3ef411cf4993466c9b95d2c91c7269d8e0b8a1e"
          },
          {
            "path": "CHANGELOG.md",
            "sha512": "497e41630720b09347688371e2dd0510c5ca1006508ab6c7520dc30e6ba2435325867d9e921c880105f6764f4783a04eb850879decb5488e65b76fdb6cdcaa3b"
          },
          {
            "path": "README.md",
            "sha512": "57031fc88a2b5981690dfd699b11eeb9d9c7876f44c4238a5a566a87c3ef6695fd987d9aa88254566eadd9bc9bdcbf8d63b97593e5cbd192ac6ea8154b86c012"

          }
        ]
      }
    },
    {
      "entry": "identity/v1alpha2",
      "value": {
        "identity": {
          "pgpPublicKeyUrl": "https://keybase.io/tronbox/pgp_keys.asc"
        }
      }
    },
    {
      "entry": "npmCompatiblePackageJson/v1alpha2",
      "value": {
        "packageJsonProperties": [
          "author",
          "authors",
          "bin",
          "bugs",
          "dependencies",
          "description",
          "devDependencies",
          "homepage",
          "keywords",
          "name",
          "namespace",
          "originalAuthor",
          "publishConfig",
          "repository",
          "scripts",
          "version"
        ],
        "sha512": "afd16062cbd44a32b5141c82ee4fc722212e8c5b325556e49598fc4c2cc459355fc5074fe72120c4d96e4f5fb4446230e3f561c8182f434f5f13ea8b1f6375ea"
      }
    },
    {
      "entry": "packageJson/v1alpha2",
      "value": {
        "packageJson": {
          "name": "tronbox",
          "namespace": "tronprotocol",
          "version": "2.7.18",
          "description": "TronBox - Simple development framework for Tron",
          "keywords": [
            "TronBox",
            "TRON",
            "Solidity",
            "Truffle",
            "Contract"
          ],
          "scripts": {
            "build": "scripts/build.sh",
            "test": "echo \"Error: tests will be fixed soon in a new release\" && exit 1",
            "prepare": "npm run build",
            "lint": "find src -name '*.js' | xargs node_modules/.bin/eslint"
          },
          "dependencies": {
            "@truffle/contract-sources": "^0.1.6",
            "@truffle/error": "0.0.7",
            "@truffle/expect": "0.0.11",
            "@truffle/solidity-utils": "^1.2.5",
            "ajv": "^6.10.2",
            "async": "2.6.1",
            "axios": "^0.18.0",
            "bignumber.js": "^7.2.1",
            "chai": "4.1.2",
            "chalk": "^2.4.1",
            "chokidar": "^1.4.2",
            "colors": "^1.1.2",
            "cpr": "^0.4.3",
            "debug": "^3.1.0",
            "del": "^2.2.0",
            "diff": ">=3.5.0",
            "ethjs-abi": "0.1.8",
            "ethpm": "0.0.16",
            "ethpm-registry": "0.1.0-next.3",
            "finalhandler": "^1.1.2",
            "find-up": "^4.1.0",
            "fs-extra": "^8.1.0",
            "github-download": "^0.5.0",
            "graphlib": "^2.1.7",
            "homedir": "^0.6.0",
            "lodash": "^4.17.15",
            "mkdirp": "^0.5.1",
            "mocha": "5.2.0",
            "node-dir": "0.1.17",
            "node-emoji": "^1.8.1",
            "original-require": "1.0.1",
            "request": "^2.88.0",
            "safe-eval": "^0.4.1",
            "semver": "^6.1.1",
            "serve-static": "^1.10.0",
            "solc": "0.8.0",
            "source-map-support": "^0.5.3",
            "spawn-args": "^0.1.0",
            "superagent": "^5.1.0",
            "temp": "^0.8.3",
            "tronweb": "^2.10.0",
            "vcsurl": "^0.1.1",
            "web3-mock": "1.0.1",
            "yargs": "^8.0.2"
          },
          "devDependencies": {
            "@babel/cli": "^7.6.4",
            "@babel/core": "^7.6.4",
            "@babel/plugin-transform-runtime": "^7.7.6",
            "@babel/preset-env": "^7.6.3",
            "electron": "^6.0.12",
            "eslint": "^6.6.0",
            "eslint-plugin-node": "^10.0.0",
            "glob": "^7.1.2",
            "js-scrypt": "^0.2.0",
            "meta-npm": "^0.0.22",
            "meta-pkgs": "^0.2.0",
            "moment": "^2.24.0",
            "prepend-file": "^1.3.1",
            "shebang-loader": "0.0.1",
            "stream-buffers": "^3.0.1",
            "tmp": "0.0.33",
            "truffle-blockchain-utils": "^0.0.5"
          },
          "bin": {
            "tronbox": "build/tronbox.js"
          },
          "repository": {
            "type": "git",
            "url": "https://github.com/tronprotocol/tronbox.git"
          },
          "homepage": "https://github.com/tronprotocol/tronbox",
          "bugs": {
            "url": "https://github.com/tronprotocol/tronbox/issues"
          },
          "originalAuthor": "consensys.net",
          "author": "tron.network",
          "authors": [
            {
              "name": "Tim Coulter",
              "email": "tim@timothyjcoulter.com",
              "url": "https://github.com/tcoulter"
            },
            {
              "name": "alinger",
              "email": "alinger@forke.cn"
            },
            {
              "name": "Francesco Sullo",
              "email": "francesco@sullo.co",
              "url": "https://github.com/sullof"
            },
            {
              "name": "Kang JianCheng",
              "email": "1063303665@qq.com",
              "url": "https://github.com/kjc233"
            }
          ],
          "publishConfig": {
            "access": "public"
          }
        }
      }
    }
  ],
  "signature": "-----BEGIN PGP SIGNATURE-----\nVersion: OpenPGP.js v4.10.9\nComment: https://openpgpjs.org\n\nwsFzBAEBCAAGBQJgCnNGACEJEAEScGf7i0tYFiEEuL4l7hUU5AsLzHjPARJw\nZ/uLS1g/Og/9EVIu0SW5EZJ+V6lvfBsD3p43bTLig1gFKmZArBL5emSoGMvA\nNixGhEi7uPfl6OYto89gwr84wD3apXh7dxFANAKVeadEFCp9qZKT6WTPG5Ai\n7AHWtDp+eV6ydbtiAlSZhrz3feGuk1Dm3uzr99n+qSVwTWwfZUQp0D8nxsTa\nMj09gmP++mbv8M5kCvW1X68abNcw8zHUWJ5pVhhszgDsw03xud693/F4TJr1\nZiX4miKHlwnPkdHQ2LfEhONDbVDSmMd8wdYCMurrAVeC/6uuk1TQNmkg8naw\n+BbfVRNirPsmxZbQKz2FV3Iwo382STMm10nX8NiX9mxTmNP2G63XjDBzk3Lg\ng1YvL3FBitfcffRn8UxRXSEhOQdR+5ero6V55+g08JnkotSZHFHI19vbxm12\nOUjopI7nRyxIjgWz2VyEGeB0aKBFfKiKS1urximAx3yQODnmU4N7h2mvbjae\n7SPKgOIUQGZoZDD18p9YKr7ZVdovyDtyoC2H5o48HIEYeIo0scsns6EvQQmY\nm7H9qnMkbXRjpbza4KSuCcK0l0JXsSDJkpk4lLMbHhqP5fYsD3XFUWZ9JnRP\ngD8wFwvCs1Rea+MmSgCV2I9qWHLCj7aRt/9r0Rm6ahTiIsqQRXEXWSy+B4pz\nrEmUEI1545WJw5Ox+wE7TYD1pmiFBgZYDUY=\n=JOs2\n-----END PGP SIGNATURE-----\n"
}